adaptive_cards/__init__.py
adaptive_cards/card.py
adaptive_cards/client.py
adaptive_cards/types.py
adaptive_cards/utils.py
adaptive_cards/validation.py
adaptive_cards/schemas/schema-1.0.json
adaptive_cards/schemas/schema-1.1.json
adaptive_cards/schemas/schema-1.2.json
adaptive_cards/schemas/schema-1.3.json
adaptive_cards/schemas/schema-1.4.json
adaptive_cards/schemas/schema-1.5.json
adaptive_cards/schemas/schema-1.6.json
adaptive_cards_py-0.4.2.dist-info/METADATA
adaptive_cards_py-0.4.2.dist-info/WHEEL
adaptive_cards_py-0.4.2.dist-info/licenses/LICENSE
adaptive_cards_py-0.4.2.dist-info/RECORD
