Metadata-Version: 2.4
Name: adaptive-cards-py
Version: 0.4.2
Summary: Python wrapper library for building beautiful adaptive cards
Project-URL: Homepage, https://github.com/dennis6p/adaptive-cards-py
License: MIT License
License-File: LICENSE
Keywords: adaptivecards,adaptivecardsio,bot,cards,python,ui
Classifier: License :: OSI Approved :: MIT License
Classifier: Programming Language :: Python
Classifier: Programming Language :: Python :: 3
Requires-Python: >=3.10
Requires-Dist: jsonschema
Requires-Dist: mypy>=1.15.0
Requires-Dist: pydantic>=2.10.6
Requires-Dist: requests
Requires-Dist: result>=0.17.0
